tosend/__init__.py
tosend/client.py
tosend/exceptions.py
tosend/py.typed
tosend/types.py
tosend-1.0.0.dist-info/licenses/LICENSE
tosend-1.0.0.dist-info/METADATA
tosend-1.0.0.dist-info/WHEEL
tosend-1.0.0.dist-info/top_level.txt
tosend-1.0.0.dist-info/RECORD
