Metadata-Version: 2.4
Name: tosend
Version: 1.0.0
Summary: Official Python SDK for the ToSend email API
Author-email: ToSend <support@tosend.com>
License: MIT
Project-URL: Homepage, https://tosend.com
Project-URL: Documentation, https://tosend.com/docs
Project-URL: Repository, https://github.com/tosend/tosend-python
Project-URL: Issues, https://github.com/tosend/tosend-python/issues
Keywords: email,api,tosend,transactional,mail
Classifier: Development Status :: 5 - Production/Stable
Classifier: Intended Audience :: Developers
Classifier: License :: OSI Approved :: MIT License
Classifier: Operating System :: OS Independent
Classifier: Programming Language :: Python :: 3
Classifier: Programming Language :: Python :: 3.8
Classifier: Programming Language :: Python :: 3.9
Classifier: Programming Language :: Python :: 3.10
Classifier: Programming Language :: Python :: 3.11
Classifier: Programming Language :: Python :: 3.12
Classifier: Topic :: Communications :: Email
Classifier: Typing :: Typed
Requires-Python: >=3.8
License-File: LICENSE
Dynamic: license-file
